setup.py
the_count/__init__.py
the_count/core.py
the_count.egg-info/PKG-INFO
the_count.egg-info/SOURCES.txt
the_count.egg-info/dependency_links.txt
the_count.egg-info/top_level.txt
the_count/proxies/__init__.py
the_count/proxies/converter.py
the_count/proxies/core.py