Metadata-Version: 1.0
Name: the-count
Version: 0.4.1
Summary: Handy class for counting things
Home-page: UNKNOWN
Author: Brian Lauber
Author-email: constructible.truth@gmail.com
License: UNKNOWN
Platform: UNKNOWN
